pydace/__init__.py
pydace/correlation/__init__.py
pydace/regression/__init__.py
pydace/utils/__init__.py
pydace/utils/matrixdivide.py
pydace/utils/optimizers/__init__.py
pydace-0.1.4.dist-info/LICENSE
pydace-0.1.4.dist-info/METADATA
pydace-0.1.4.dist-info/WHEEL
pydace-0.1.4.dist-info/top_level.txt
pydace-0.1.4.dist-info/RECORD
