Metadata-Version: 2.1
Name: pydace
Version: 0.1.4
Summary: Design and Analysis of Computational Experiments as python toolbox.
Home-page: https://github.com/feslima/pydace
Author: Felipe Souza Lima
Author-email: felipe.lima@eq.ufcg.edu.br
License: Apache License 2.0
Keywords: surrogate,metamodel
Platform: UNKNOWN
Classifier: Programming Language :: Python :: 3.6
Classifier: License :: OSI Approved :: Apache Software License
Classifier: Operating System :: OS Independent
Classifier: Topic :: Scientific/Engineering
Requires-Python: >=3.7
License-File: LICENSE
Requires-Dist: numpy (>=1.16)
Requires-Dist: scipy (>=1.2.0)
Requires-Dist: pyDOE2 (>=1.2.1)
